{
  "title": "Sapiens",
  "subtitle": "A Brief History of Humankind",
  "authors": [
    {
      "authorFName": "Yuval",
      "authorMName": "Noah",
      "authorLName": "Harari"
    }
  ],
  "publishedDate": "2015-02-10",
  "pageCount": 464,

  "categories": ["Science"],
  "imageLink": "http://books.google.com/books/content?id=FmyBAwAAQBAJ&printsec=frontcover&img=1&zoom=1&edge=curl&source=gbs_api",

  "userRating": 10,
  "tags": ["Science", "Favorites", "Read", "2022"],
  "notes": [
    "This book is my favorite!",
    "I've actually read this book twice recently",
    "Otherwise I'll just forget what happened!"
  ]
}
